transport_cba/__init__.py
transport_cba/param_container.py
transport_cba/road_cba.py
transport_cba/sample_projects.py
transport_cba/examples/bypass_capex.csv
transport_cba/examples/bypass_intensities_0.csv
transport_cba/examples/bypass_intensities_1.csv
transport_cba/examples/bypass_road_params.csv
transport_cba/examples/bypass_velocities_0.csv
transport_cba/examples/bypass_velocities_1.csv
transport_cba/examples/cba_sample_bypass.xlsx
transport_cba/parameters/svk/accident_cost.csv
transport_cba/parameters/svk/accident_rate.csv
transport_cba/parameters/svk/conversion_factors.csv
transport_cba/parameters/svk/cpi.csv
transport_cba/parameters/svk/emission_cost.csv
transport_cba/parameters/svk/emission_rate.csv
transport_cba/parameters/svk/freight_occupancy.csv
transport_cba/parameters/svk/fuel_consumption.csv
transport_cba/parameters/svk/fuel_cost.csv
transport_cba/parameters/svk/fuel_density.csv
transport_cba/parameters/svk/fuel_ratio.csv
transport_cba/parameters/svk/gdp_growth.csv
transport_cba/parameters/svk/greenhouse_cost.csv
transport_cba/parameters/svk/greenhouse_rate.csv
transport_cba/parameters/svk/max_velocities.csv
transport_cba/parameters/svk/noise.csv
transport_cba/parameters/svk/operation_cost.csv
transport_cba/parameters/svk/passenger_occupancy.csv
transport_cba/parameters/svk/residual_value.csv
transport_cba/parameters/svk/sample_input.csv
transport_cba/parameters/svk/toll_operation_cost.csv
transport_cba/parameters/svk/trip_purpose.csv
transport_cba/parameters/svk/voc.csv
transport_cba/parameters/svk/vtts.csv
transport_cba-0.1.2.dist-info/LICENSE
transport_cba-0.1.2.dist-info/METADATA
transport_cba-0.1.2.dist-info/WHEEL
transport_cba-0.1.2.dist-info/top_level.txt
transport_cba-0.1.2.dist-info/RECORD
