Metadata-Version: 2.1
Name: transport-cba
Version: 0.1.2
Summary: A Python package for cost-benefit analysis of infrastructure projects
Home-page: https://github.com/transport-cba/transport-cba
Author: Peter Vanya
Author-email: peter.vanya@gmail.com
Keywords: cost benefit analysis
Classifier: Programming Language :: Python :: 3
Classifier: License :: OSI Approved :: MIT License
Classifier: Operating System :: OS Independent
Requires-Python: >=3
License-File: LICENSE
Requires-Dist: numpy <2,>=1.16
Requires-Dist: pandas <1.3,>=0.24
Requires-Dist: numpy-financial >=1.0.0
Requires-Dist: openpyxl >=3.0.10
